kry.py
kry-2025.5.22.dist-info/METADATA
kry-2025.5.22.dist-info/WHEEL
kry-2025.5.22.dist-info/top_level.txt
kry-2025.5.22.dist-info/RECORD
