Metadata-Version: 2.4
Name: kry
Version: 2025.5.22
Summary: kry.py - Simple cryptography library
License-Expression: Unlicense OR CC0-1.0
Project-URL: homepage, https://github.com/krylib/kry
Classifier: Topic :: Security :: Cryptography
